pyperion/__init__.py
pyperion/hyperion.py
PyPerion-1.0.7.dist-info/METADATA
PyPerion-1.0.7.dist-info/WHEEL
PyPerion-1.0.7.dist-info/top_level.txt
PyPerion-1.0.7.dist-info/RECORD
