Metadata-Version: 2.1
Name: PyPerion
Version: 1.0.7
Summary: An python obfuscator that use hyperion
Home-page: https://github.com/Ayumu-1337/PyPerion
Author: Ayumu
Author-email: Ayumu-1337@proton.me
Project-URL: Bug Tracker, https://github.com/Ayumu-1337/PyPerion/issues
Classifier: Programming Language :: Python :: 3
Classifier: License :: OSI Approved :: MIT License
Classifier: Operating System :: OS Independent
Requires-Python: >=3.6
